classifierscores
