Metadata-Version: 1.1
Name: classifierscores
Version: 0.0.2
Summary: Basic Classifiers with train and validation scores
Home-page: UNKNOWN
Author: Aatir Kirmani
Author-email: kirmaniaatir@gmail.com
License: MIT
Keywords: model classication scores classifier
Platform: UNKNOWN
Classifier: Development Status :: 5 - Production/Stable
Classifier: Intended Audience :: Education
Classifier: Operating System :: Microsoft :: Windows :: Windows 10
Classifier: License :: OSI Approved :: MIT License
Classifier: Programming Language :: Python :: 3
